{
  "conversation_id": "ecf_train_1244",
  "utterances": [
    {
      "utterance_id": "u1",
      "speaker": "Chandler",
      "text": "And here we go .",
      "emotion": "neutral",
      "timestamp": 0.0
    },
    {
      "utterance_id": "u2",
      "speaker": "Joey",
      "text": "I saw this movie once where there was a door and no one knew what was behind it , and when they finally got it open millions and millions and millions of bugs came pouring out and they feasted on human flesh .",
      "emotion": "disgust",
      "timestamp": 2.5,
      "emotion_cause": {
        "utterance_id": "u2",
        "span": "2_I saw this movie once where there was a door and no one knew what was behind it , and when they finally got it open millions and millions and millions of bugs came pouring out and they feasted on human flesh .",
        "modality": "text"
      }
    },
    {
      "utterance_id": "u3",
      "speaker": "Joey",
      "text": "You know , it would not kill you to respect your wife privacy !",
      "emotion": "anger",
      "timestamp": 5.0
    },
    {
      "utterance_id": "u4",
      "speaker": "Joey",
      "text": "Stupid closet full of bugs !",
      "emotion": "fear",
      "timestamp": 7.5,
      "emotion_cause": {
        "utterance_id": "u4",
        "span": "4_Stupid closet full of bugs !",
        "modality": "text"
      }
    },
    {
      "utterance_id": "u5",
      "speaker": "Rachel",
      "text": "Joey . Joey , something feels weird and not good weird . I do not ... Whoa ! !",
      "emotion": "fear",
      "timestamp": 10.0,
      "emotion_cause": {
        "utterance_id": "u5",
        "span": "5_something feels weird and not good weird .",
        "modality": "text"
      }
    },
    {
      "utterance_id": "u6",
      "speaker": "Joey",
      "text": "Do not worry , Ok ? When my sisters were pregnant they got every weird feeling in the book , it was always nothing .",
      "emotion": "neutral",
      "timestamp": 12.5
    },
    {
      "utterance_id": "u7",
      "speaker": "Rachel",
      "text": "Really ?",
      "emotion": "surprise",
      "timestamp": 15.0,
      "emotion_cause": {
        "utterance_id": "u7",
        "span": "6_When my sisters were pregnant they got every weird feeling in the book , it was always nothing .",
        "modality": "text"
      }
    },
    {
      "utterance_id": "u8",
      "speaker": "Joey",
      "text": "Absolutely . But we will stop by the hospital just to be sure . I will page Ross on the way .",
      "emotion": "neutral",
      "timestamp": 17.5
    },
    {
      "utterance_id": "u9",
      "speaker": "Rachel",
      "text": "Okay , oh , God ... Ow .",
      "emotion": "fear",
      "timestamp": 20.0
    },
    {
      "utterance_id": "u10",
      "speaker": "Joey",
      "text": "Okay Rach ... Rach ... Rach look at me , look at me , everything gonna be fine , trust me . Trust me . Take my hand . Here we go .",
      "emotion": "neutral",
      "timestamp": 22.5
    },
    {
      "utterance_id": "u11",
      "speaker": "Joey",
      "text": "Ow ! Crushing bones !",
      "emotion": "surprise",
      "timestamp": 25.0,
      "emotion_cause": {
        "utterance_id": "u11",
        "span": "11_Crushing bones !",
        "modality": "text"
      }
    }
  ],
  "video_path": null,
  "audio_path": null,
  "metadata": {
    "source": "huggingface",
    "split": "train",
    "original_id": 1244,
    "num_utterances": 11,
    "num_emotion_pairs": 5
  }
}