{
  "conversation_id": "ecf_train_1048",
  "utterances": [
    {
      "utterance_id": "u1",
      "speaker": "Ross",
      "text": "and the miracle was that that little bit of oil that should have just lasted just one day , burned for",
      "emotion": "neutral",
      "timestamp": 0.0
    },
    {
      "utterance_id": "u2",
      "speaker": "Ben",
      "text": "Eight whole days .",
      "emotion": "neutral",
      "timestamp": 2.5
    },
    {
      "utterance_id": "u3",
      "speaker": "Ross",
      "text": "That is right , and that is why we celebrate Hanukkah today . The end .",
      "emotion": "joy",
      "timestamp": 5.0,
      "emotion_cause": {
        "utterance_id": "u3",
        "span": "3_That is right , and that is why we celebrate Hanukkah today .",
        "modality": "text"
      }
    },
    {
      "utterance_id": "u4",
      "speaker": "Ben",
      "text": "Awesome !",
      "emotion": "joy",
      "timestamp": 7.5,
      "emotion_cause": {
        "utterance_id": "u4",
        "span": "4_Awesome !",
        "modality": "text"
      }
    },
    {
      "utterance_id": "u5",
      "speaker": "Ross",
      "text": "Yeah ?",
      "emotion": "joy",
      "timestamp": 10.0,
      "emotion_cause": {
        "utterance_id": "u5",
        "span": "4_Awesome !",
        "modality": "text"
      }
    },
    {
      "utterance_id": "u6",
      "speaker": "Chandler",
      "text": "My favorite part was when Superman flew all the Jews out of Egypt .",
      "emotion": "neutral",
      "timestamp": 12.5
    },
    {
      "utterance_id": "u7",
      "speaker": "Ross",
      "text": "The Armadillo was actually not so thrilled about that part !",
      "emotion": "neutral",
      "timestamp": 15.0
    },
    {
      "utterance_id": "u8",
      "speaker": "Rachel",
      "text": "Hey !",
      "emotion": "joy",
      "timestamp": 17.5,
      "emotion_cause": {
        "utterance_id": "u8",
        "span": "8_Hey !",
        "modality": "text"
      }
    },
    {
      "utterance_id": "u9",
      "speaker": "Phoebe",
      "text": "Oh .",
      "emotion": "neutral",
      "timestamp": 20.0
    },
    {
      "utterance_id": "u10",
      "speaker": "Rachel",
      "text": "Wow ! It looks like the Easter Bunny funeral in here .",
      "emotion": "surprise",
      "timestamp": 22.5,
      "emotion_cause": {
        "utterance_id": "u10",
        "span": "10_It looks like the Easter Bunny funeral in here .",
        "modality": "text"
      }
    },
    {
      "utterance_id": "u11",
      "speaker": "Ross",
      "text": "Come on , come on , we are ... we are ... we are lighting the candles !",
      "emotion": "joy",
      "timestamp": 25.0,
      "emotion_cause": {
        "utterance_id": "u11",
        "span": "11_we are ... we are ... we are lighting the candles !",
        "modality": "text"
      }
    },
    {
      "utterance_id": "u12",
      "speaker": "Rachel",
      "text": "Oh .",
      "emotion": "neutral",
      "timestamp": 27.5
    },
    {
      "utterance_id": "u13",
      "speaker": "Phoebe",
      "text": "Oh .",
      "emotion": "neutral",
      "timestamp": 30.0
    },
    {
      "utterance_id": "u14",
      "speaker": "Phoebe",
      "text": "Okay , I understand why Superman is here ,",
      "emotion": "neutral",
      "timestamp": 32.5
    }
  ],
  "video_path": null,
  "audio_path": null,
  "metadata": {
    "source": "huggingface",
    "split": "train",
    "original_id": 1048,
    "num_utterances": 14,
    "num_emotion_pairs": 6
  }
}