{
  "conversation_id": "ecf_train_312",
  "utterances": [
    {
      "utterance_id": "u1",
      "speaker": "Gunther",
      "text": "Hey guys .",
      "emotion": "neutral",
      "timestamp": 0.0
    },
    {
      "utterance_id": "u2",
      "speaker": "Monica",
      "text": "Hey Gunther . Hi . I mean you are going out on a date with the noisy guy upstairs ?",
      "emotion": "surprise",
      "timestamp": 2.5,
      "emotion_cause": {
        "utterance_id": "u2",
        "span": "2_you are going out on a date with the noisy guy upstairs",
        "modality": "text"
      }
    },
    {
      "utterance_id": "u3",
      "speaker": "Phoebe",
      "text": "Well , he is very charming .",
      "emotion": "neutral",
      "timestamp": 5.0
    },
    {
      "utterance_id": "u4",
      "speaker": "Monica",
      "text": "I know , he is too charming , but if you two start going out , then it is just gonna make it so much harder for me to hate him .",
      "emotion": "disgust",
      "timestamp": 7.5,
      "emotion_cause": {
        "utterance_id": "u4",
        "span": "4_he is too charming , but if you two start going out , then it is just gonna make it so much harder for me to hate him .",
        "modality": "text"
      }
    },
    {
      "utterance_id": "u5",
      "speaker": "Phoebe",
      "text": "Well , you are just gonna have to try .",
      "emotion": "neutral",
      "timestamp": 10.0
    },
    {
      "utterance_id": "u6",
      "speaker": "Monica",
      "text": "Joey , where are the Jell ... o shots ?",
      "emotion": "neutral",
      "timestamp": 12.5
    },
    {
      "utterance_id": "u7",
      "speaker": "Joey",
      "text": "I do not know , Chandler is supposed to be passin em around ...",
      "emotion": "neutral",
      "timestamp": 15.0
    }
  ],
  "video_path": null,
  "audio_path": null,
  "metadata": {
    "source": "huggingface",
    "split": "train",
    "original_id": 312,
    "num_utterances": 7,
    "num_emotion_pairs": 2
  }
}