{
  "conversation_id": "ecf_train_815",
  "utterances": [
    {
      "utterance_id": "u1",
      "speaker": "Guy #1",
      "text": "Nice car !",
      "emotion": "joy",
      "timestamp": 0.0,
      "emotion_cause": {
        "utterance_id": "u1",
        "span": "1_Nice car !",
        "modality": "text"
      }
    },
    {
      "utterance_id": "u2",
      "speaker": "Joey",
      "text": "Yeah , it is not mine .",
      "emotion": "neutral",
      "timestamp": 2.5
    },
    {
      "utterance_id": "u3",
      "speaker": "Woman",
      "text": "I love your car .",
      "emotion": "joy",
      "timestamp": 5.0,
      "emotion_cause": {
        "utterance_id": "u3",
        "span": "3_I love your car .",
        "modality": "text"
      }
    },
    {
      "utterance_id": "u4",
      "speaker": "Joey",
      "text": "Yeah , it is mine .",
      "emotion": "neutral",
      "timestamp": 7.5
    },
    {
      "utterance_id": "u5",
      "speaker": "Woman",
      "text": "I bet it is fast .",
      "emotion": "neutral",
      "timestamp": 10.0
    },
    {
      "utterance_id": "u6",
      "speaker": "Joey",
      "text": "Me too ! Yeah . And comfortable . Do uh , do you like leather seats ?",
      "emotion": "neutral",
      "timestamp": 12.5
    },
    {
      "utterance_id": "u7",
      "speaker": "Woman",
      "text": "Yeah !",
      "emotion": "joy",
      "timestamp": 15.0,
      "emotion_cause": {
        "utterance_id": "u7",
        "span": "7_Yeah !",
        "modality": "text"
      }
    },
    {
      "utterance_id": "u8",
      "speaker": "Joey",
      "text": "It is got em !",
      "emotion": "joy",
      "timestamp": 17.5,
      "emotion_cause": {
        "utterance_id": "u8",
        "span": "8_It is got em !",
        "modality": "text"
      }
    }
  ],
  "video_path": null,
  "audio_path": null,
  "metadata": {
    "source": "huggingface",
    "split": "train",
    "original_id": 815,
    "num_utterances": 8,
    "num_emotion_pairs": 7
  }
}