{
  "conversation_id": "ecf_train_350",
  "utterances": [
    {
      "utterance_id": "u1",
      "speaker": "Phoebe",
      "text": "Smelly cat , smelly cat , what are they feeding you ? Smelly cat , smelly cat , it is not your fault .",
      "emotion": "neutral",
      "timestamp": 0.0
    },
    {
      "utterance_id": "u2",
      "speaker": "Leslie",
      "text": "Wow , that is great .",
      "emotion": "joy",
      "timestamp": 2.5,
      "emotion_cause": {
        "utterance_id": "u2",
        "span": "2_that is great .",
        "modality": "text"
      }
    },
    {
      "utterance_id": "u3",
      "speaker": "Phoebe",
      "text": "Oh , yeah !",
      "emotion": "joy",
      "timestamp": 5.0,
      "emotion_cause": {
        "utterance_id": "u3",
        "span": "2_that is great .",
        "modality": "text"
      }
    },
    {
      "utterance_id": "u4",
      "speaker": "Leslie",
      "text": "You know you could totally sell this . It would be perfect for like umm , a kitty litter campaign .",
      "emotion": "joy",
      "timestamp": 7.5,
      "emotion_cause": {
        "utterance_id": "u4",
        "span": "4_you could totally sell this . It would be perfect for like umm , a kitty litter campaign .",
        "modality": "text"
      }
    },
    {
      "utterance_id": "u5",
      "speaker": "Phoebe",
      "text": "I ... , a jingle ? No , no ... no ... no , no .",
      "emotion": "neutral",
      "timestamp": 10.0
    },
    {
      "utterance_id": "u6",
      "speaker": "Leslie",
      "text": "What ? Why not ? You could make a ton of money .",
      "emotion": "surprise",
      "timestamp": 12.5,
      "emotion_cause": {
        "utterance_id": "u6",
        "span": "5_a jingle ? No , no ... no ... no , no .",
        "modality": "text"
      }
    },
    {
      "utterance_id": "u7",
      "speaker": "Phoebe",
      "text": "Okay , well if I was in this for the money , I would be a millionaire by now , you know .",
      "emotion": "neutral",
      "timestamp": 15.0
    },
    {
      "utterance_id": "u8",
      "speaker": "Phoebe",
      "text": "You just got to get out of that jingle head sweetie .",
      "emotion": "neutral",
      "timestamp": 17.5
    }
  ],
  "video_path": null,
  "audio_path": null,
  "metadata": {
    "source": "huggingface",
    "split": "train",
    "original_id": 350,
    "num_utterances": 8,
    "num_emotion_pairs": 5
  }
}