{
  "conversation_id": "ecf_train_1254",
  "utterances": [
    {
      "utterance_id": "u1",
      "speaker": "Chandler",
      "text": "Oh my God , honey we are so meant to be together . We both have copies of the Annie soundtrack .",
      "emotion": "joy",
      "timestamp": 0.0,
      "emotion_cause": {
        "utterance_id": "u1",
        "span": "1_we are so meant to be together . We both have copies of the Annie soundtrack .",
        "modality": "text"
      }
    },
    {
      "utterance_id": "u2",
      "speaker": "Monica",
      "text": "Honey , both yours .",
      "emotion": "neutral",
      "timestamp": 2.5
    },
    {
      "utterance_id": "u3",
      "speaker": "Rachel",
      "text": "Hey ! Great advice on that Joey thing !",
      "emotion": "joy",
      "timestamp": 5.0,
      "emotion_cause": {
        "utterance_id": "u3",
        "span": "3_Great advice on that Joey thing !",
        "modality": "text"
      }
    },
    {
      "utterance_id": "u4",
      "speaker": "Monica",
      "text": "Yeah ? The work problem ?",
      "emotion": "joy",
      "timestamp": 7.5,
      "emotion_cause": {
        "utterance_id": "u4",
        "span": "3_Great advice on that Joey thing !",
        "modality": "text"
      }
    },
    {
      "utterance_id": "u5",
      "speaker": "Rachel",
      "text": "Oh it was perfect ! I mean it really felt like he was my friend again .",
      "emotion": "joy",
      "timestamp": 10.0,
      "emotion_cause": {
        "utterance_id": "u5",
        "span": "5_it was perfect ! I mean it really felt like he was my friend again .",
        "modality": "text"
      }
    },
    {
      "utterance_id": "u6",
      "speaker": "Chandler",
      "text": "What problem did you tell him you had ?",
      "emotion": "neutral",
      "timestamp": 12.5
    },
    {
      "utterance_id": "u7",
      "speaker": "Rachel",
      "text": "Oh that is not important . The point is , I really ... I think everything gonna be okay .",
      "emotion": "neutral",
      "timestamp": 15.0
    }
  ],
  "video_path": null,
  "audio_path": null,
  "metadata": {
    "source": "huggingface",
    "split": "train",
    "original_id": 1254,
    "num_utterances": 7,
    "num_emotion_pairs": 4
  }
}