{
  "conversation_id": "ecf_train_1197",
  "utterances": [
    {
      "utterance_id": "u1",
      "speaker": "Phoebe",
      "text": "Hey !",
      "emotion": "joy",
      "timestamp": 0.0,
      "emotion_cause": {
        "utterance_id": "u1",
        "span": "1_Hey !",
        "modality": "text"
      }
    },
    {
      "utterance_id": "u2",
      "speaker": "Eric",
      "text": "Welcome back !",
      "emotion": "joy",
      "timestamp": 2.5,
      "emotion_cause": {
        "utterance_id": "u2",
        "span": "2_Welcome back !",
        "modality": "text"
      }
    },
    {
      "utterance_id": "u3",
      "speaker": "Phoebe",
      "text": "Hey ! Can we pick up where we left off ?",
      "emotion": "joy",
      "timestamp": 5.0,
      "emotion_cause": {
        "utterance_id": "u3",
        "span": "3_Can we pick up where we left off ?",
        "modality": "text"
      }
    },
    {
      "utterance_id": "u4",
      "speaker": "Eric",
      "text": "I do not know , I am still pretty tired out from this afternoon .",
      "emotion": "neutral",
      "timestamp": 7.5
    },
    {
      "utterance_id": "u5",
      "speaker": "Phoebe",
      "text": "Why ?",
      "emotion": "surprise",
      "timestamp": 10.0,
      "emotion_cause": {
        "utterance_id": "u5",
        "span": "4_I am still pretty tired out from this afternoon .",
        "modality": "text"
      }
    },
    {
      "utterance_id": "u6",
      "speaker": "Eric",
      "text": "Uh , the sex .",
      "emotion": "neutral",
      "timestamp": 12.5
    },
    {
      "utterance_id": "u7",
      "speaker": "Phoebe",
      "text": "What sex ?",
      "emotion": "surprise",
      "timestamp": 15.0,
      "emotion_cause": {
        "utterance_id": "u7",
        "span": "6_the sex .",
        "modality": "text"
      }
    },
    {
      "utterance_id": "u8",
      "speaker": "Eric",
      "text": "Our sex .",
      "emotion": "neutral",
      "timestamp": 17.5
    },
    {
      "utterance_id": "u9",
      "speaker": "Phoebe",
      "text": "We did not have sex .",
      "emotion": "surprise",
      "timestamp": 20.0,
      "emotion_cause": {
        "utterance_id": "u9",
        "span": "9_We did not have sex .",
        "modality": "text"
      }
    },
    {
      "utterance_id": "u10",
      "speaker": "Eric",
      "text": "Well if I did not have sex with you , I had sex with someone that looked an awful lot like",
      "emotion": "joy",
      "timestamp": 22.5,
      "emotion_cause": {
        "utterance_id": "u10",
        "span": "10_if I did not have sex with you , I had sex with someone that looked an awful lot like",
        "modality": "text"
      }
    },
    {
      "utterance_id": "u11",
      "speaker": "Phoebe",
      "text": "Ew ! Ew ! Ew ! Ew ! Ew ! Ew !",
      "emotion": "disgust",
      "timestamp": 25.0,
      "emotion_cause": {
        "utterance_id": "u11",
        "span": "10_if I did not have sex with you , I had sex with someone that looked an awful lot like",
        "modality": "text"
      }
    },
    {
      "utterance_id": "u12",
      "speaker": "Eric",
      "text": "Oh no ! Oh no ! Oh no ! Oh no ! No ! No ! No !",
      "emotion": "disgust",
      "timestamp": 27.5,
      "emotion_cause": {
        "utterance_id": "u12",
        "span": "10_if I did not have sex with you , I had sex with someone that looked an awful lot like",
        "modality": "text"
      }
    }
  ],
  "video_path": null,
  "audio_path": null,
  "metadata": {
    "source": "huggingface",
    "split": "train",
    "original_id": 1197,
    "num_utterances": 12,
    "num_emotion_pairs": 14
  }
}