{
  "conversation_id": "ecf_train_9",
  "utterances": [
    {
      "utterance_id": "u1",
      "speaker": "Rachel",
      "text": "Barry ?",
      "emotion": "surprise",
      "timestamp": 0.0
    },
    {
      "utterance_id": "u2",
      "speaker": "Barry",
      "text": "C mon in .",
      "emotion": "neutral",
      "timestamp": 2.5
    },
    {
      "utterance_id": "u3",
      "speaker": "Rachel",
      "text": "Are you sure ?",
      "emotion": "surprise",
      "timestamp": 5.0,
      "emotion_cause": {
        "utterance_id": "u3",
        "span": "2_C mon in .",
        "modality": "text"
      }
    },
    {
      "utterance_id": "u4",
      "speaker": "Barry",
      "text": "Yeah ! It is fine , it is fine . Robbie gonna be here for hours .",
      "emotion": "neutral",
      "timestamp": 7.5
    },
    {
      "utterance_id": "u5",
      "speaker": "Robbie",
      "text": "Huh ? !",
      "emotion": "surprise",
      "timestamp": 10.0,
      "emotion_cause": {
        "utterance_id": "u5",
        "span": "4_Robbie gonna be here for hours .",
        "modality": "text"
      }
    },
    {
      "utterance_id": "u6",
      "speaker": "Barry",
      "text": "So , how you doin ?",
      "emotion": "neutral",
      "timestamp": 12.5
    }
  ],
  "video_path": null,
  "audio_path": null,
  "metadata": {
    "source": "huggingface",
    "split": "train",
    "original_id": 9,
    "num_utterances": 6,
    "num_emotion_pairs": 2
  }
}