{
  "conversation_id": "ecf_train_609",
  "utterances": [
    {
      "utterance_id": "u1",
      "speaker": "Joey",
      "text": "Hey , Pheebs ! It is Joey !",
      "emotion": "joy",
      "timestamp": 0.0,
      "emotion_cause": {
        "utterance_id": "u1",
        "span": "1_Hey , Pheebs !",
        "modality": "text"
      }
    },
    {
      "utterance_id": "u2",
      "speaker": "Phoebe",
      "text": "Hey , Joey !",
      "emotion": "joy",
      "timestamp": 2.5,
      "emotion_cause": {
        "utterance_id": "u2",
        "span": "2_Hey , Joey !",
        "modality": "text"
      }
    },
    {
      "utterance_id": "u3",
      "speaker": "Phoebe",
      "text": "Hey !",
      "emotion": "joy",
      "timestamp": 5.0
    },
    {
      "utterance_id": "u4",
      "speaker": "Phoebe",
      "text": "Ooh !",
      "emotion": "joy",
      "timestamp": 7.5,
      "emotion_cause": {
        "utterance_id": "u4",
        "span": "6_I just saw someone on the ... that looks just like you on the subway .",
        "modality": "text"
      }
    },
    {
      "utterance_id": "u5",
      "speaker": "Phoebe",
      "text": "Ooh !",
      "emotion": "joy",
      "timestamp": 10.0,
      "emotion_cause": {
        "utterance_id": "u5",
        "span": "6_I just saw someone on the ... that looks just like you on the subway .",
        "modality": "text"
      }
    },
    {
      "utterance_id": "u6",
      "speaker": "Phoebe",
      "text": "I just saw someone on the ... that looks just like you on the subway .",
      "emotion": "joy",
      "timestamp": 12.5,
      "emotion_cause": {
        "utterance_id": "u6",
        "span": "6_I just saw someone on the ... that looks just like you on the subway .",
        "modality": "text"
      }
    },
    {
      "utterance_id": "u7",
      "speaker": "Phoebe",
      "text": "And I was gonna go over and say hi ! but then I figured , he does not care if he looks like you .",
      "emotion": "joy",
      "timestamp": 15.0,
      "emotion_cause": {
        "utterance_id": "u7",
        "span": "6_I just saw someone on the ... that looks just like you on the subway .",
        "modality": "text"
      }
    },
    {
      "utterance_id": "u8",
      "speaker": "Joey",
      "text": "That just cost me four bucks . But uh listen , I just called to see how the chick and the duck are doing ?",
      "emotion": "neutral",
      "timestamp": 17.5
    },
    {
      "utterance_id": "u9",
      "speaker": "Phoebe",
      "text": "Ohh , they are having a great time with their Aunt Phoebe !",
      "emotion": "joy",
      "timestamp": 20.0,
      "emotion_cause": {
        "utterance_id": "u9",
        "span": "9_they are having a great time with their Aunt Phoebe !",
        "modality": "text"
      }
    },
    {
      "utterance_id": "u10",
      "speaker": "Joey",
      "text": "Kinda , but I have just been having way too much fun .",
      "emotion": "joy",
      "timestamp": 22.5,
      "emotion_cause": {
        "utterance_id": "u10",
        "span": "10_I have just been having way too much fun .",
        "modality": "text"
      }
    },
    {
      "utterance_id": "u11",
      "speaker": "Phoebe",
      "text": "So you are not homesick yet ?",
      "emotion": "joy",
      "timestamp": 25.0,
      "emotion_cause": {
        "utterance_id": "u11",
        "span": "11_you are not homesick yet ?",
        "modality": "text"
      }
    },
    {
      "utterance_id": "u12",
      "speaker": "Joey",
      "text": "No , I do not think so .",
      "emotion": "neutral",
      "timestamp": 27.5
    },
    {
      "utterance_id": "u13",
      "speaker": "Phoebe",
      "text": "All right , the seven of us miss you .",
      "emotion": "neutral",
      "timestamp": 30.0
    }
  ],
  "video_path": null,
  "audio_path": null,
  "metadata": {
    "source": "huggingface",
    "split": "train",
    "original_id": 609,
    "num_utterances": 13,
    "num_emotion_pairs": 11
  }
}