{
  "conversation_id": "ecf_train_1250",
  "utterances": [
    {
      "utterance_id": "u1",
      "speaker": "Joey",
      "text": "Okay . Okay , I can do this . I can tell her how I feel .",
      "emotion": "fear",
      "timestamp": 0.0
    },
    {
      "utterance_id": "u2",
      "speaker": "Joey",
      "text": "Just uh , just stand up straight .",
      "emotion": "fear",
      "timestamp": 2.5
    },
    {
      "utterance_id": "u3",
      "speaker": "Joey",
      "text": "Take a couple deep breaths .",
      "emotion": "fear",
      "timestamp": 5.0
    },
    {
      "utterance_id": "u4",
      "speaker": "Joey",
      "text": "Look confident .",
      "emotion": "fear",
      "timestamp": 7.5
    },
    {
      "utterance_id": "u5",
      "speaker": "Rachel",
      "text": "Joey ? What up ?",
      "emotion": "surprise",
      "timestamp": 10.0
    },
    {
      "utterance_id": "u6",
      "speaker": "Joey",
      "text": "I uh , I just came by because I ... I want to talk to you about something .",
      "emotion": "fear",
      "timestamp": 12.5
    },
    {
      "utterance_id": "u7",
      "speaker": "Rachel",
      "text": "Okay what up ?",
      "emotion": "neutral",
      "timestamp": 15.0
    }
  ],
  "video_path": null,
  "audio_path": null,
  "metadata": {
    "source": "huggingface",
    "split": "train",
    "original_id": 1250,
    "num_utterances": 7,
    "num_emotion_pairs": 0
  }
}