{
  "conversation_id": "ecf_train_19",
  "utterances": [
    {
      "utterance_id": "u1",
      "speaker": "Monica",
      "text": "How does she do that ?",
      "emotion": "surprise",
      "timestamp": 0.0,
      "emotion_cause": {
        "utterance_id": "u1",
        "span": "2_sleep in a public place",
        "modality": "text"
      }
    },
    {
      "utterance_id": "u2",
      "speaker": "Ross",
      "text": "I cannot sleep in a public place .",
      "emotion": "neutral",
      "timestamp": 2.5
    },
    {
      "utterance_id": "u3",
      "speaker": "Monica",
      "text": "Would you look at her ? She is so peaceful .",
      "emotion": "joy",
      "timestamp": 5.0,
      "emotion_cause": {
        "utterance_id": "u3",
        "span": "3_She is so peaceful .",
        "modality": "text"
      }
    },
    {
      "utterance_id": "u4",
      "speaker": "Phoebe",
      "text": "Oh ! What what what ! ... Hi .",
      "emotion": "surprise",
      "timestamp": 7.5
    },
    {
      "utterance_id": "u5",
      "speaker": "Ross",
      "text": "It is okay , you know , you just nodded off again .",
      "emotion": "neutral",
      "timestamp": 10.0
    },
    {
      "utterance_id": "u6",
      "speaker": "Monica",
      "text": "What going on with you ?",
      "emotion": "surprise",
      "timestamp": 12.5,
      "emotion_cause": {
        "utterance_id": "u6",
        "span": "5_you just nodded off again .",
        "modality": "text"
      }
    },
    {
      "utterance_id": "u7",
      "speaker": "Phoebe",
      "text": "I got no sleep last night !",
      "emotion": "anger",
      "timestamp": 15.0,
      "emotion_cause": {
        "utterance_id": "u7",
        "span": "7_I got no sleep last night !",
        "modality": "text"
      }
    },
    {
      "utterance_id": "u8",
      "speaker": "Ross",
      "text": "Why ?",
      "emotion": "neutral",
      "timestamp": 17.5
    },
    {
      "utterance_id": "u9",
      "speaker": "Phoebe",
      "text": "My grandmother has this new boyfriend , and they are both kind of insecure in bed ... and deaf .",
      "emotion": "disgust",
      "timestamp": 20.0,
      "emotion_cause": {
        "utterance_id": "u9",
        "span": "9_My grandmother has this new boyfriend , and they are both kind of insecure in bed ... and deaf .",
        "modality": "text"
      }
    },
    {
      "utterance_id": "u10",
      "speaker": "Phoebe",
      "text": "So they are constantly , like , having to reassure each other that they are having a good time .",
      "emotion": "neutral",
      "timestamp": 22.5
    },
    {
      "utterance_id": "u11",
      "speaker": "Phoebe",
      "text": "You have no idea how loud they are !",
      "emotion": "disgust",
      "timestamp": 25.0,
      "emotion_cause": {
        "utterance_id": "u11",
        "span": "11_You have no idea how loud they are !",
        "modality": "text"
      }
    },
    {
      "utterance_id": "u12",
      "speaker": "Monica",
      "text": "Well , if you want , you can stay with Rachel and me tonight .",
      "emotion": "neutral",
      "timestamp": 27.5
    },
    {
      "utterance_id": "u13",
      "speaker": "Phoebe",
      "text": "Thanks .",
      "emotion": "joy",
      "timestamp": 30.0,
      "emotion_cause": {
        "utterance_id": "u13",
        "span": "12_if you want , you can stay with Rachel and me tonight .",
        "modality": "text"
      }
    }
  ],
  "video_path": null,
  "audio_path": null,
  "metadata": {
    "source": "huggingface",
    "split": "train",
    "original_id": 19,
    "num_utterances": 13,
    "num_emotion_pairs": 8
  }
}